fast_pip/__init__.py
fast_pip/__main__.py
fast_pip/fast_pip.py
hyperpip-0.4.0.dist-info/licenses/LICENSE
hyperpip-0.4.0.dist-info/METADATA
hyperpip-0.4.0.dist-info/WHEEL
hyperpip-0.4.0.dist-info/entry_points.txt
hyperpip-0.4.0.dist-info/top_level.txt
hyperpip-0.4.0.dist-info/RECORD
